Divider/00_rtl/divider_setup.v

//`define DIV1
`define DIV2
//`define DIV3

`ifdef DIV2
    `define DEF_DIVIDER_DIV       (8'd2)        // output latency [clock]  1 : DIVIDEND_BITDEPTH,  2 : DIVIDEND_BITDEPTH / 2, ...
`elsif DIV3
    `define DEF_DIVIDER_DIV       (8'd3)        // output latency [clock]  1 : DIVIDEND_BITDEPTH,  2 : DIVIDEND_BITDEPTH / 2, ...
`else
    `define DEF_DIVIDER_DIV       (8'd1)       // output latency [clock]  1 : DIVIDEND_BITDEPTH,  2 : DIVIDEND_BITDEPTH / 2, ...
`endif

`define DEF_DIVIDEND_BITDEPTH     (8'd16                                      )      // always DIVIDEND_BIPDEPTH >= DIVISOR_BITDEPTH
`define DEF_DIVISOR_BITDEPTH      (8'd16                                      )
`define DEF_DIVIDER_COUNT         (`DEF_DIVIDEND_BITDEPTH / `DEF_DIVIDER_DIV  )      // output latency [clock]  1 : DIVIDEND_BITDEPTH,  2 : DIVIDEND_BITDEPTH / 2, ...
`define DEF_DIVIDER_REMAIN        (`DEF_DIVIDEND_BITDEPTH % `DEF_DIVIDER_DIV  )      // This value should be '0'

Divider/00_rtl/divider.v
`timescale 10ns / 100ps

`include "../00_rtl/divider_setup.v"

module divider #
(
    parameter   DIVIDEND_BITDEPTH   = `DEF_DIVIDEND_BITDEPTH  ,       // always DIVIDEND_BIPDEPTH >= DIVISOR_BITDEPTH
    parameter   DIVISOR_BITDEPTH    = `DEF_DIVISOR_BITDEPTH   ,
    parameter   DIVIDER_DIV         = `DEF_DIVIDER_DIV        ,       // output latency [clock]  1 : DIVIDEND_BITDEPTH,  2 : DIVIDEND_BITDEPTH / 2, ...
    parameter   DIVIDER_COUNT       = `DEF_DIVIDER_COUNT      ,       // DIVIDEND_BIPDEPTH / DIVIDER_DIV
    parameter   DIVIDER_REMAIN      = `DEF_DIVIDER_REMAIN             // DIVIDEND_BIPDEPTH % DIVIDER_DIV ###### NOT USED #####
)(
    input                           i_rstn          ,
    input                           i_sclk          ,
    input                           i_input_valid   ,
    input   [DIVIDEND_BITDEPTH-1:0] i_dividend      ,
    input   [ DIVISOR_BITDEPTH-1:0] i_divisor       ,
    output                          o_output_valid  ,
    output  [DIVIDEND_BITDEPTH-1:0] o_quotient      ,
    output  [DIVIDEND_BITDEPTH-1:0] o_remainder     
);
    reg     [DIVIDER_COUNT-1:0]     r_input_valid_d;

    wire    w_vld_upd   =   i_input_valid || (|r_input_valid_d);
    always @(posedge i_sclk or negedge i_rstn) 
         if (!i_rstn)   r_input_valid_d <= {DIVIDER_COUNT{1'd0}};
    else if (w_vld_upd) r_input_valid_d <= #1 {r_input_valid_d[DIVIDER_COUNT-2:0], i_input_valid};

    wire    [DIVIDEND_BITDEPTH:0]       w_dividend[0:DIVIDEND_BITDEPTH-1]   ;    
    wire    [DIVISOR_BITDEPTH-1:0]      w_divisor[0:DIVIDEND_BITDEPTH-1]    ;    
    wire    [DIVIDEND_BITDEPTH-1:0]     w_quotient                          ;
    wire    [DIVIDEND_BITDEPTH:0]       w_remainder[0:DIVIDEND_BITDEPTH-1]  ;    

    reg     [DIVIDEND_BITDEPTH:0]       r_dividend[0:DIVIDER_COUNT-1]       ;
    reg     [DIVISOR_BITDEPTH-1:0]      r_divisor[0:DIVIDER_COUNT-1]        ;
    reg     [DIVIDEND_BITDEPTH-1:0]     r_quotient[0:DIVIDER_COUNT-1]       ;
    reg     [DIVIDEND_BITDEPTH:0]       r_remainder[0:DIVIDER_COUNT-1]      ;

    wire    [DIVIDER_COUNT-1:0]         w_div_upd   ;

    `ifdef DIV2
        assign w_dividend[0]  =   {{(DIVIDEND_BITDEPTH){1'd0}} , i_dividend[DIVIDEND_BITDEPTH-1]}               ; 
        assign w_divisor[0]   =   {{(DIVIDEND_BITDEPTH-DIVISOR_BITDEPTH){1'd0}}, i_divisor}                     ;
        assign w_quotient[1]  =   w_dividend[0] < w_divisor[0] ? 1'd0 : 1'd1                                    ;
        assign w_remainder[0] =   w_quotient[1] ? w_dividend[0] - w_divisor[0] : w_dividend[0]                  ;

        assign w_dividend[1]  =  {w_remainder[0], i_dividend[DIVIDEND_BITDEPTH-2]}                              ;    
        assign w_divisor[1]   =   {{(DIVIDEND_BITDEPTH-DIVISOR_BITDEPTH){1'd0}}, i_divisor}                     ;
        assign w_quotient[0]  =   w_dividend[1] < w_divisor[1] ? 1'd0 : 1'd1                                    ;
        assign w_remainder[1] =   w_quotient[0] ? w_dividend[1] - w_divisor[1] : w_dividend[1]                  ;
    `elsif DIV3
        assign w_dividend[0]  =  {{(DIVIDEND_BITDEPTH){1'd0}} ,   i_dividend[DIVIDEND_BITDEPTH-1]}              ; 
        assign w_divisor[0]   =   {{(DIVIDEND_BITDEPTH-DIVISOR_BITDEPTH){1'd0}}, i_divisor}                     ;
        assign w_quotient[2]  =   w_dividend[0] < w_divisor[0] ? 1'd0 : 1'd1                                    ;
        assign w_remainder[0] =   w_quotient[2] ? w_dividend[0] - w_divisor[0] : w_dividend[0]                  ;

        assign w_dividend[1]  =  {w_remainder[0], i_dividend[DIVIDEND_BITDEPTH-2]}                              ;    
        assign w_divisor[1]   =   {{(DIVIDEND_BITDEPTH-DIVISOR_BITDEPTH){1'd0}}, i_divisor}                     ;
        assign w_quotient[1]  =   w_dividend[1] < w_divisor[1] ? 1'd0 : 1'd1                                    ;
        assign w_remainder[1] =   w_quotient[1] ? w_dividend[1] - w_divisor[1] : w_dividend[1]                  ;

        assign w_dividend[2]  =  {w_remainder[1], i_dividend[DIVIDEND_BITDEPTH-3]}                              ;    
        assign w_divisor[2]   =   {{(DIVIDEND_BITDEPTH-DIVISOR_BITDEPTH){1'd0}}, i_divisor}                     ;
        assign w_quotient[0]  =   w_dividend[2] < w_divisor[2] ? 1'd0 : 1'd1                                    ;
        assign w_remainder[2] =   w_quotient[0] ? w_dividend[2] - w_divisor[2] : w_dividend[2]                  ;
    `else
        assign w_dividend[0]  =  {{(DIVIDEND_BITDEPTH){1'd0}} ,   i_dividend[DIVIDEND_BITDEPTH-1]}              ; 
        assign w_divisor[0]   =  {{(DIVIDEND_BITDEPTH-DIVISOR_BITDEPTH){1'd0}}, i_divisor}                      ;
        assign w_quotient[0]  =  w_dividend[0] < w_divisor[0] ? 1'd0 : 1'd1                                     ;
        assign w_remainder[0] =  w_quotient[0] ? w_dividend[0] - w_divisor[0] : w_dividend[0]                   ;
    `endif

    always  @(posedge i_sclk or negedge i_rstn)
        if (!i_rstn) begin
            r_dividend[0]   <=  {(DIVIDEND_BITDEPTH+1){1'd0}}     ;
            r_divisor[0]    <=  {(DIVISOR_BITDEPTH){1'd0}}      ;
            r_quotient[0]   <=  {(DIVIDEND_BITDEPTH){1'd0}}     ;
            r_remainder[0]  <=  {(DIVIDEND_BITDEPTH+1){1'd0}}     ;
        end
    else if(i_input_valid)   begin
            r_dividend[0]   <=  #1 {1'd0, i_dividend[DIVIDEND_BITDEPTH-1-DIVIDER_DIV:0] , {DIVIDER_DIV{1'd0}}}  ;
            r_divisor[0]    <=  #1 w_divisor[0]                                                                 ;
            r_quotient[0]   <=  #1 {{(DIVIDEND_BITDEPTH-DIVIDER_DIV){1'd0}}, w_quotient[DIVIDER_DIV-1:0]}       ;
            r_remainder[0]  <=  #1 w_remainder[DIVIDER_DIV-1]                                                   ;
        end

    genvar i;
    generate for ( i = 0 ; i < DIVIDER_COUNT - 1 ; i=i+1) begin : loop_for_divider
        assign  w_div_upd[i] = r_input_valid_d[i]      ;

    `ifdef DIV2
        assign w_dividend[(i+1)*DIVIDER_DIV]    = {r_remainder[i], r_dividend[i][DIVIDEND_BITDEPTH-1]}                                                          ;    
        assign w_divisor[(i+1)*DIVIDER_DIV]     = {{(DIVIDEND_BITDEPTH-DIVISOR_BITDEPTH){1'd0}}, r_divisor[i]}                                                  ;
        assign w_quotient[(i+1)*DIVIDER_DIV+1]  = w_dividend[(i+1)*DIVIDER_DIV] < w_divisor[(i+1)*DIVIDER_DIV] ? 1'd0 : 1'd1                                    ;
        assign w_remainder[(i+1)*DIVIDER_DIV]   = w_quotient[(i+1)*DIVIDER_DIV+1] ? w_dividend[(i+1)*DIVIDER_DIV] - w_divisor[(i+1)*DIVIDER_DIV]: 
                                                                                    w_dividend[(i+1)*DIVIDER_DIV]                                               ;

        assign w_dividend[(i+1)*DIVIDER_DIV+1]  = {w_remainder[(i+1)*DIVIDER_DIV], r_dividend[i][DIVIDEND_BITDEPTH-2]}                   ;    
        assign w_divisor[(i+1)*DIVIDER_DIV+1]   = {{(DIVIDEND_BITDEPTH-DIVISOR_BITDEPTH){1'd0}}, r_divisor[i]}                                                  ;
        assign w_quotient[(i+1)*DIVIDER_DIV]    = w_dividend[(i+1)*DIVIDER_DIV+1] < w_divisor[(i+1)*DIVIDER_DIV+1] ? 1'd0 : 1'd1                                ;
        assign w_remainder[(i+1)*DIVIDER_DIV+1] = w_quotient[(i+1)*DIVIDER_DIV] ? w_dividend[(i+1)*DIVIDER_DIV+1] - w_divisor[(i+1)*DIVIDER_DIV+1]: 
                                                                                  w_dividend[(i+1)*DIVIDER_DIV+1]                                               ;
    `elsif DIV3
        assign w_dividend[(i+1)*DIVIDER_DIV]    = {r_remainder[i], r_dividend[i][DIVIDEND_BITDEPTH-1]}                                                          ;    
        assign w_divisor[(i+1)*DIVIDER_DIV]     = {{(DIVIDEND_BITDEPTH-DIVISOR_BITDEPTH){1'd0}}, r_divisor[i]}                                                  ;
        assign w_quotient[(i+1)*DIVIDER_DIV+2]  = w_dividend[(i+1)*DIVIDER_DIV] < w_divisor[(i+1)*DIVIDER_DIV] ? 1'd0 : 1'd1                                    ;
        assign w_remainder[(i+1)*DIVIDER_DIV]   = w_quotient[(i+1)*DIVIDER_DIV+2] ? w_dividend[(i+1)*DIVIDER_DIV] - w_divisor[(i+1)*DIVIDER_DIV]: 
                                                                                    w_dividend[(i+1)*DIVIDER_DIV]                                               ;

        assign w_dividend[(i+1)*DIVIDER_DIV+1]  = {w_remainder[(i+1)*DIVIDER_DIV], r_dividend[i][DIVIDEND_BITDEPTH-2]}                   ;    
        assign w_divisor[(i+1)*DIVIDER_DIV+1]   = {{(DIVIDEND_BITDEPTH-DIVISOR_BITDEPTH){1'd0}}, r_divisor[i]}                                                  ;
        assign w_quotient[(i+1)*DIVIDER_DIV+1]  = w_dividend[(i+1)*DIVIDER_DIV+1] < w_divisor[(i+1)*DIVIDER_DIV+1] ? 1'd0 : 1'd1                                ;
        assign w_remainder[(i+1)*DIVIDER_DIV+1] = w_quotient[(i+1)*DIVIDER_DIV+1] ? w_dividend[(i+1)*DIVIDER_DIV+1] - w_divisor[(i+1)*DIVIDER_DIV+1]: 
                                                                                    w_dividend[(i+1)*DIVIDER_DIV+1]                                             ;

        assign w_dividend[(i+1)*DIVIDER_DIV+2]  = {w_remainder[(i+1)*DIVIDER_DIV+1], r_dividend[i][DIVIDEND_BITDEPTH-3]}                 ;    
        assign w_divisor[(i+1)*DIVIDER_DIV+2]   = {{(DIVIDEND_BITDEPTH-DIVISOR_BITDEPTH){1'd0}}, r_divisor[i]}                                                  ;
        assign w_quotient[(i+1)*DIVIDER_DIV]    = w_dividend[(i+1)*DIVIDER_DIV+2] < w_divisor[(i+1)*DIVIDER_DIV+2] ? 1'd0 : 1'd1                                ;
        assign w_remainder[(i+1)*DIVIDER_DIV+2] = w_quotient[(i+1)*DIVIDER_DIV] ? w_dividend[(i+1)*DIVIDER_DIV+2] - w_divisor[(i+1)*DIVIDER_DIV+2]: 
                                                                                  w_dividend[(i+1)*DIVIDER_DIV+2]                                               ;
    `else
        assign w_dividend[(i+1)*DIVIDER_DIV]    = {r_remainder[i], r_dividend[i][DIVIDEND_BITDEPTH-1]}                                                          ;    
        assign w_divisor[(i+1)*DIVIDER_DIV]     = {{(DIVIDEND_BITDEPTH-DIVISOR_BITDEPTH){1'd0}}, r_divisor[i]}                                                  ;
        assign w_quotient[(i+1)*DIVIDER_DIV]    = w_dividend[(i+1)*DIVIDER_DIV] < w_divisor[(i+1)*DIVIDER_DIV] ? 1'd0 : 1'd1                                    ;
        assign w_remainder[(i+1)*DIVIDER_DIV]   = w_quotient[(i+1)*DIVIDER_DIV] ? w_dividend[(i+1)*DIVIDER_DIV] - w_divisor[(i+1)*DIVIDER_DIV]: 
                                                                                  w_dividend[(i+1)*DIVIDER_DIV]                                                 ;
    `endif
        always  @(posedge i_sclk or negedge i_rstn)
        if (!i_rstn) begin
            r_dividend[i+1]   <=  {(DIVIDEND_BITDEPTH){1'd0}}       ;
            r_divisor[i+1]    <=  {(DIVIDEND_BITDEPTH){1'd0}}       ;
            r_quotient[i+1]   <=  {(DIVIDEND_BITDEPTH){1'd0}}       ;
            r_remainder[i+1]  <=  {(DIVIDEND_BITDEPTH){1'd0}}       ;
        end
        else if(w_div_upd[i])   begin
            r_dividend[i+1]   <=  #1 {r_dividend[i][DIVIDEND_BITDEPTH:0] , {DIVIDER_DIV{1'd0}} }                                                                                          ; 
            r_divisor[i+1]    <=  #1 r_divisor[i]                                                                                                                                           ;
            r_quotient[i+1]   <=  #1 {{(DIVIDEND_BITDEPTH-(i+2)*DIVIDER_DIV){1'd0}}, r_quotient[i][(i+1)*DIVIDER_DIV-1:0], w_quotient[(i+1)*DIVIDER_DIV+DIVIDER_DIV-1:(i+1)*DIVIDER_DIV]}   ;
            r_remainder[i+1]  <=  #1 w_remainder[(i+1)*DIVIDER_DIV+(DIVIDER_DIV-1)]                                                                                                         ;
        end
    end
    endgenerate

    assign          o_output_valid  =   r_input_valid_d[DIVIDER_COUNT-1] ;
    assign          o_quotient      =   r_quotient[DIVIDER_COUNT-1]      ;
    assign          o_remainder     =   r_remainder[DIVIDER_COUNT-1]     ;
endmodule

Divider/01_testbench/divider_tb.v
`timescale 10ns/100ps

`include "../00_rtl/divider_setup.v"         // File for the simulation condition 
                                             // Before operating simulation, you should modify this file.

module tb;
    parameter CLK_FREQ  = 10                 ;
    parameter VALID_NUM = 40                 ;    
    parameter R_VALID_LOW_LENGTH  = 30       ;

    initial begin
     if (`DEF_DIVIDER_REMAIN != 0) begin
          $display("[Error] DIVIDER_REMAIN is not '0'");
          $finish;
     end
    end

    reg i_rstn = 1'd0;
    reg i_sclk = 1'd0;
    reg r_data = 1'd0;
    
    always #(CLK_FREQ/2) i_sclk = ~i_sclk;

    reg [ 31:0]     r_vb_cnt            ;
    reg [ 31:0]     r_vld_high_ref_cnt  ;
    reg [ 31:0]     r_vld_high_cnt      ;
    reg [ 31:0]     r_vld_low_cnt       ;
    reg [ 31:0]     r_vld_num_cnt       ;    
    
    reg             r_active_area   ;
    reg                                 r_valid        ;
    reg                                 r_valid_d      ;
    reg   [`DEF_DIVIDEND_BITDEPTH-1:0]  r_dividend     ;
    reg   [ `DEF_DIVISOR_BITDEPTH-1:0]  r_divisor      ;
    wire                                w_output_valid ;
    wire  [`DEF_DIVIDEND_BITDEPTH-1:0]  w_quotient     ;
    wire  [`DEF_DIVIDEND_BITDEPTH-1:0]  w_remainder    ;    

    always  @(posedge i_sclk or negedge i_rstn)
         if (!i_rstn)   r_vb_cnt <= 32'd0               ;
    else if (!r_valid)  r_vb_cnt <= #1 r_vb_cnt + 32'd1 ;
    else                r_vb_cnt <= #1 32'd0            ;

    wire    w_vld_start     = r_vb_cnt == 32'd500           ;         // reset condition
    wire    w_vld_num_rst   = r_vld_num_cnt == VALID_NUM    ;         // simulation done flag
    always  @(posedge i_sclk or negedge i_rstn)
         if (!i_rstn)       r_active_area   <= 1'd0     ;
    else if (w_vld_num_rst) r_active_area   <= #1 1'd0  ;
    else if (w_vld_start)   r_active_area   <= #1 1'd1  ;

    always  @(posedge i_sclk or negedge i_rstn)
         if (!i_rstn)   r_vld_high_ref_cnt <= 32'd0                             ;
    else if (w_vld_f)   r_vld_high_ref_cnt <= #1 r_vld_high_ref_cnt + 32'd1     ;

    always  @(posedge i_sclk or negedge i_rstn)
         if (!i_rstn)   r_vld_high_cnt <= 32'd0                     ;
    else if (r_valid)   r_vld_high_cnt <= #1 r_vld_high_cnt + 32'd1 ;
    else                r_vld_high_cnt <= #1 32'd0                  ;

    always  @(posedge i_sclk or negedge i_rstn)
         if (!i_rstn)   r_vld_low_cnt <= 32'd0                     ;
    else if (!r_valid)  r_vld_low_cnt <= #1 r_vld_low_cnt + 32'd1  ;
    else                r_vld_low_cnt <= #1 32'd0                  ;

    wire    w_vld_rst   =   r_vld_high_cnt == r_vld_high_ref_cnt                    ;
    wire    w_vld_ac_st =   r_vld_low_cnt == R_VALID_LOW_LENGTH && r_active_area    ;
    always  @(posedge i_sclk or negedge i_rstn)
         if (!i_rstn)       r_valid <= 1'd0     ;
    else if (w_vld_start)   r_valid <= #1 1'd1  ;
    else if (w_vld_rst)     r_valid <= #1 1'd0  ;
    else if (w_vld_ac_st)   r_valid <= #1 1'd1  ;

    wire    w_vld_r     =   r_valid && !r_valid_d   ;
    wire    w_vld_f     =  !r_valid &&  r_valid_d   ;
    always  @(posedge i_sclk or negedge i_rstn)
         if (!i_rstn)       r_valid_d   <=  1'd0        ;
    else                    r_valid_d   <= #1 r_valid   ;

    always  @(posedge i_sclk or negedge i_rstn)
         if (!i_rstn)       r_vld_num_cnt <= 32'd0                     ;
    else if (w_vld_num_rst) r_vld_num_cnt <= #1 32'd0                  ;
    else if (w_vld_f)       r_vld_num_cnt <= #1 r_vld_num_cnt + 32'd1  ;

     always  @(posedge i_sclk or negedge i_rstn)
          if (!i_rstn)       r_dividend <= {(`DEF_DIVISOR_BITDEPTH){1'd0}}       ;
     else if (r_valid)       r_dividend <= #1 ($random % 65536) ;

     always  @(posedge i_sclk or negedge i_rstn)
          if (!i_rstn)       r_divisor <= {(`DEF_DIVISOR_BITDEPTH){1'd0}}       ;
     else if (r_valid)       r_divisor <= #1 ($random % 2 == 1) ? ($random % 65536) + 1 :  ($random % 32) + 1 ;

    divider # (
        .DIVIDEND_BITDEPTH   (`DEF_DIVIDEND_BITDEPTH  ),       // always DIVIDEND_BIPDEPTH >= DIVISOR_BITDEPTH
        .DIVISOR_BITDEPTH    (`DEF_DIVISOR_BITDEPTH   ),
        .DIVIDER_DIV         (`DEF_DIVIDER_DIV        ),       // output latency [clock]  1 : DIVIDEND_BITDEPTH,  2 : DIVIDEND_BITDEPTH / 2, ...
        .DIVIDER_COUNT       (`DEF_DIVIDER_COUNT      ),       // output latency [clock]  1 : DIVIDEND_BITDEPTH,  2 : DIVIDEND_BITDEPTH / 2, ...
        .DIVIDER_REMAIN      (`DEF_DIVIDER_REMAIN     )        // Should be '0'
    ) u_divider (
        .i_rstn              (i_rstn        ),
        .i_sclk              (i_sclk        ),
        .i_input_valid       (r_valid_d     ),
        .i_dividend          (r_dividend    ),
        .i_divisor           (r_divisor     ),
        .o_output_valid      (w_output_valid),
        .o_quotient          (w_quotient    ),
        .o_remainder         (w_remainder   )
);

     initial begin
          $dumpfile("divider.vcd");
          $dumpvars(-1,tb);  //  
     end

     integer div_input_info_file  ;
     integer div_input_file       ;
     integer div_output_file      ;
     initial begin
          div_input_info_file = $fopen("div_input_info.txt", "w");
          div_input_file = $fopen("div_input.txt", "w");
          div_output_file = $fopen("div_output.txt", "w");
     end

     always @(posedge i_sclk)
          if (r_valid_d) $fwrite(div_input_info_file, "Dividend : %d\tDivisor : %d\tQuotient : %d\tRemainder : %d\n", r_dividend, r_divisor,r_dividend / r_divisor,r_dividend %r_divisor );  

     always @(posedge i_sclk)
          if (r_valid_d) $fwrite(div_input_file, "[Input_Calc] \tQuotient : %d\tRemainder : %d\n", r_dividend / r_divisor,r_dividend %r_divisor );  

     always @(posedge i_sclk)
          if (w_output_valid) $fwrite(div_output_file, "[Output_Sim] \tQuotient : %d\tRemainder : %d\n", w_quotient,w_remainder );

     initial begin
          #10 i_rstn = 1'd1;
          #2000;
          @(w_vld_num_rst);
          #2000;
          $fclose(div_input_info_file);
          $fclose(div_input_file);
          $fclose(div_output_file);
          $finish;
     end
//iverilog -o divider.vvp divider.v divider_tb.v
//vvp divider.vvp
//gtkwave divider.vcd
endmodule

Divider/01_testbench/divider.vcd
$date
	Sun Jan 08 14:34:48 2023
$end
$version
	Icarus Verilog
$end
$timescale
	100ps
$end
$scope module tb $end
$var wire 1 ! w_vld_ac_st $end
$var wire 1 " w_vld_f $end
$var wire 1 # w_vld_r $end
$var wire 1 $ w_vld_start $end
$var wire 1 % w_vld_rst $end
$var wire 1 & w_vld_num_rst $end
$var wire 16 ' w_remainder [15:0] $end
$var wire 16 ( w_quotient [15:0] $end
$var wire 1 ) w_output_valid $end
$var parameter 32 * CLK_FREQ $end
$var parameter 32 + R_VALID_LOW_LENGTH $end
$var parameter 32 , VALID_NUM $end
$var reg 1 - i_rstn $end
$var reg 1 . i_sclk $end
$var reg 1 / r_active_area $end
$var reg 1 0 r_data $end
$var reg 16 1 r_dividend [15:0] $end
$var reg 16 2 r_divisor [15:0] $end
$var reg 1 3 r_valid $end
$var reg 1 4 r_valid_d $end
$var reg 32 5 r_vb_cnt [31:0] $end
$var reg 32 6 r_vld_high_cnt [31:0] $end
$var reg 32 7 r_vld_high_ref_cnt [31:0] $end
$var reg 32 8 r_vld_low_cnt [31:0] $end
$var reg 32 9 r_vld_num_cnt [31:0] $end
$var integer 32 : div_input_file [31:0] $end
$var integer 32 ; div_input_info_file [31:0] $end
$var integer 32 < div_output_file [31:0] $end
$scope module u_divider $end
$var wire 16 = i_dividend [15:0] $end
$var wire 16 > i_divisor [15:0] $end
$var wire 1 4 i_input_valid $end
$var wire 1 - i_rstn $end
$var wire 1 . i_sclk $end
$var wire 16 ? o_quotient [15:0] $end
$var wire 1 @ w_vld_upd $end
$var wire 16 A w_quotient [15:0] $end
$var wire 8 B w_div_upd [7:0] $end
$var wire 16 C o_remainder [15:0] $end
$var wire 1 ) o_output_valid $end
$var parameter 8 D DIVIDEND_BITDEPTH $end
$var parameter 8 E DIVIDER_COUNT $end
$var parameter 8 F DIVIDER_DIV $end
$var parameter 8 G DIVIDER_REMAIN $end
$var parameter 8 H DIVISOR_BITDEPTH $end
$var reg 8 I r_input_valid_d [7:0] $end
$scope begin loop_for_divider[0] $end
$var parameter 2 J i $end
$upscope $end
$scope begin loop_for_divider[1] $end
$var parameter 2 K i $end
$upscope $end
$scope begin loop_for_divider[2] $end
$var parameter 3 L i $end
$upscope $end
$scope begin loop_for_divider[3] $end
$var parameter 3 M i $end
$upscope $end
$scope begin loop_for_divider[4] $end
$var parameter 4 N i $end
$upscope $end
$scope begin loop_for_divider[5] $end
$var parameter 4 O i $end
$upscope $end
$scope begin loop_for_divider[6] $end
$var parameter 4 P i $end
$upscope $end
$upscope $end
$upscope $end
$enddefinitions $end
$comment Show the parameter values. $end
$dumpall
b110 P
b101 O
b100 N
b11 M
b10 L
b1 K
b0 J
b10000 H
b0 G
b10 F
b1000 E
b10000 D
b101000 ,
b11110 +
b1010 *
$end
#0
$dumpvars
b0 I
b0 C
bz0000000 B
b11111111111111xx A
x@
b0 ?
bx >
bx =
b10000000000000000000000000000101 <
b10000000000000000000000000000011 ;
b10000000000000000000000000000100 :
bx 9
bx 8
bx 7
bx 6
bx 5
x4
x3
bx 2
bx 1
00
x/
0.
0-
0)
b0 (
b0 '
x&
x%
x$
x#
x"
x!
$end
#500
b1111111111111111 A
0!
0#
0@
0"
0$
b0 5
0/
1%
b0 7
b0 6
b0 8
03
04
0&
b0 9
b0 1
b0 =
b0 2
b0 >
1.
#1000
0.
1-
#1500
1.
#1600
b1 8
b1 5
#2000
0.
#2500
1.
#2600
b10 5
b10 8
#3000
0.
#3500
1.
#3600
b11 8
b11 5
#4000
0.
#4500
1.
#4600
b100 5
b100 8
#5000
0.
#5500
1.
#5600
b101 8
b101 5
#6000
0.
#6500
1.
#6600
b110 5
b110 8
#7000
0.
#7500
1.
#7600
b111 8
b111 5
#8000
0.
#8500
1.
#8600
b1000 5
b1000 8
#9000
0.
#9500
1.
#9600
b1001 8
b1001 5
#10000
0.
#10500
1.
#10600
b1010 5
b1010 8
#11000
0.
#11500
1.
#11600
b1011 8
b1011 5
#12000
0.
#12500
1.
#12600
b1100 5
b1100 8
#13000
0.
#13500
1.
#13600
b1101 8
b1101 5
#14000
0.
#14500
1.
#14600
b1110 5
b1110 8
#15000
0.
#15500
1.
#15600
b1111 8
b1111 5
#16000
0.
#16500
1.
#16600
b10000 5
b10000 8
#17000
0.
#17500
1.
#17600
b10001 8
b10001 5
#18000
0.
#18500
1.
#18600
b10010 5
b10010 8
#19000
0.
#19500
1.
#19600
b10011 8
b10011 5
#20000
0.
#20500
1.
#20600
b10100 5
b10100 8
#21000
0.
#21500
1.
#21600
b10101 8
b10101 5
#22000
0.
#22500
1.
#22600
b10110 5
b10110 8
#23000
0.
#23500
1.
#23600
b10111 8
b10111 5
#24000
0.
#24500
1.
#24600
b11000 5
b11000 8
#25000
0.
#25500
1.
#25600
b11001 8
b11001 5
#26000
0.
#26500
1.
#26600
b11010 5
b11010 8
#27000
0.
#27500
1.
#27600
b11011 8
b11011 5
#28000
0.
#28500
1.
#28600
b11100 5
b11100 8
#29000
0.
#29500
1.
#29600
b11101 8
b11101 5
#30000
0.
#30500
1.
#30600
b11110 5
b11110 8
#31000
0.
#31500
1.
#31600
b11111 8
b11111 5
#32000
0.
#32500
1.
#32600
b100000 5
b100000 8
#33000
0.
#33500
1.
#33600
b100001 8
b100001 5
#34000
0.
#34500
1.
#34600
b100010 5
b100010 8
#35000
0.
#35500
1.
#35600
b100011 8
b100011 5
#36000
0.
#36500
1.
#36600
b100100 5
b100100 8
#37000
0.
#37500
1.
#37600
b100101 8
b100101 5
#38000
0.
#38500
1.
#38600
b100110 5
b100110 8
#39000
0.
#39500
1.
#39600
b100111 8
b100111 5
#40000
0.
#40500
1.
#40600
b101000 5
b101000 8
#41000
0.
#41500
1.
#41600
b101001 8
b101001 5
#42000
0.
#42500
1.
#42600
b101010 5
b101010 8
#43000
0.
#43500
1.
#43600
b101011 8
b101011 5
#44000
0.
#44500
1.
#44600
b101100 5
b101100 8
#45000
0.
#45500
1.
#45600
b101101 8
b101101 5
#46000
0.
#46500
1.
#46600
b101110 5
b101110 8
#47000
0.
#47500
1.
#47600
b101111 8
b101111 5
#48000
0.
#48500
1.
#48600
b110000 5
b110000 8
#49000
0.
#49500
1.
#49600
b110001 8
b110001 5
#50000
0.
#50500
1.
#50600
b110010 5
b110010 8
#51000
0.
#51500
1.
#51600
b110011 8
b110011 5
#52000
0.
#52500
1.
#52600
b110100 5
b110100 8
#53000
0.
#53500
1.
#53600
b110101 8
b110101 5
#54000
0.
#54500
1.
#54600
b110110 5
b110110 8
#55000
0.
#55500
1.
#55600
b110111 8
b110111 5
#56000
0.
#56500
1.
#56600
b111000 5
b111000 8
#57000
0.
#57500
1.
#57600
b111001 8
b111001 5
#58000
0.
#58500
1.
#58600
b111010 5
b111010 8
#59000
0.
#59500
1.
#59600
b111011 8
b111011 5
#60000
0.
#60500
1.
#60600
b111100 5
b111100 8
#61000
0.
#61500
1.
#61600
b111101 8
b111101 5
#62000
0.
#62500
1.
#62600
b111110 5
b111110 8
#63000
0.
#63500
1.
#63600
b111111 8
b111111 5
#64000
0.
#64500
1.
#64600
b1000000 5
b1000000 8
#65000
0.
#65500
1.
#65600
b1000001 8
b1000001 5
#66000
0.
#66500
1.
#66600
b1000010 5
b1000010 8
#67000
0.
#67500
1.
#67600
b1000011 8
b1000011 5
#68000
0.
#68500
1.
#68600
b1000100 5
b1000100 8
#69000
0.
#69500
1.
#69600
b1000101 8
b1000101 5
#70000
0.
#70500
1.
#70600
b1000110 5
b1000110 8
#71000
0.
#71500
1.
#71600
b1000111 8
b1000111 5
#72000
0.
#72500
1.
#72600
b1001000 5
b1001000 8
#73000
0.
#73500
1.
#73600
b1001001 8
b1001001 5
#74000
0.
#74500
1.
#74600
b1001010 5
b1001010 8
#75000
0.
#75500
1.
#75600
b1001011 8
b1001011 5
#76000
0.
#76500
1.
#76600
b1001100 5
b1001100 8
#77000
0.
#77500
1.
#77600
b1001101 8
b1001101 5
#78000
0.
#78500
1.
#78600
b1001110 5
b1001110 8
#79000
0.
#79500
1.
#79600
b1001111 8
b1001111 5
#80000
0.
#80500
1.
#80600
b1010000 5
b1010000 8
#81000
0.
#81500
1.
#81600
b1010001 8
b1010001 5
#82000
0.
#82500
1.
#82600
b1010010 5
b1010010 8
#83000
0.
#83500
1.
#83600
b1010011 8
b1010011 5
#84000
0.
#84500
1.
#84600
b1010100 5
b1010100 8
#85000
0.
#85500
1.
#85600
b1010101 8
b1010101 5
#86000
0.
#86500
1.
#86600
b1010110 5
b1010110 8
#87000
0.
#87500
1.
#87600
b1010111 8
b1010111 5
#88000
0.
#88500
1.
#88600
b1011000 5
b1011000 8
#89000
0.
#89500
1.
#89600
b1011001 8
b1011001 5
#90000
0.
#90500
1.
#90600
b1011010 5
b1011010 8
#91000
0.
#91500
1.
#91600
b1011011 8
b1011011 5
#92000
0.
#92500
1.
#92600
b1011100 5
b1011100 8
#93000
0.
#93500
1.
#93600
b1011101 8
b1011101 5
#94000
0.
#94500
1.
#94600
b1011110 5
b1011110 8
#95000
0.
#95500
1.
#95600
b1011111 8
b1011111 5
#96000
0.
#96500
1.
#96600
b1100000 5
b1100000 8
#97000
0.
#97500
1.
#97600
b1100001 8
b1100001 5
#98000
0.
#98500
1.
#98600
b1100010 5
b1100010 8
#99000
0.
#99500
1.
#99600
b1100011 8
b1100011 5
#100000
0.
#100500
1.
#100600
b1100100 5
b1100100 8
#101000
0.
#101500
1.
#101600
b1100101 8
b1100101 5
#102000
0.
#102500
1.
#102600
b1100110 5
b1100110 8
#103000
0.
#103500
1.
#103600
b1100111 8
b1100111 5
